LICENSE
MANIFEST.in
README.md
distribute_setup.py
setup.py
dabble/__init__.py
dabble/util.py
dabble.egg-info/PKG-INFO
dabble.egg-info/SOURCES.txt
dabble.egg-info/dependency_links.txt
dabble.egg-info/top_level.txt
dabble/backends/__init__.py
dabble/backends/fs.py
dabble/backends/mongodb.py
test/__init__.py
test/test_backend.py