Metadata-Version: 1.0
Name: dabble
Version: 0.2.3
Summary: Simple A/B testing framework
Home-page: https://github.com/dcrosta/dabble
Author: Dan Crosta
Author-email: dcrosta@late.am
License: BSD
Keywords: python web abtest split ab a/b test
Platform: UNKNOWN
Classifier: Programming Language :: Python
Classifier: Programming Language :: Python :: 2.4
Classifier: Programming Language :: Python :: 2.5
Classifier: Programming Language :: Python :: 2.6
Classifier: Programming Language :: Python :: 2.7
